poetryjpgtopng_test/__init__.py
poetryjpgtopng_test/jpgTopng.py
poetryjpgtopng_test-0.1.0.dist-info/METADATA
poetryjpgtopng_test-0.1.0.dist-info/WHEEL
poetryjpgtopng_test-0.1.0.dist-info/RECORD
